veritasgraph/__init__.py
veritasgraph/cli.py
veritasgraph/models.py
veritasgraph/py.typed
veritasgraph/tree_extractor.py
veritasgraph/vision.py
veritasgraph-0.3.0.dist-info/METADATA
veritasgraph-0.3.0.dist-info/WHEEL
veritasgraph-0.3.0.dist-info/entry_points.txt
veritasgraph-0.3.0.dist-info/licenses/LICENSE
veritasgraph-0.3.0.dist-info/RECORD
