Metadata-Version: 2.4
Name: veritasgraph
Version: 0.3.0
Summary: Enterprise-Grade Graph RAG Framework - Don't Chunk. Graph. Vision-Native Document Analysis with Hierarchical Tree Support
Project-URL: Homepage, https://github.com/bibinprathap/VeritasGraph
Project-URL: Documentation, https://bibinprathap.github.io/VeritasGraph/
Project-URL: Repository, https://github.com/bibinprathap/VeritasGraph
Project-URL: Issues, https://github.com/bibinprathap/VeritasGraph/issues
Project-URL: Changelog, https://github.com/bibinprathap/VeritasGraph/releases
Author-email: Bibin Prathap <bibinprathap@gmail.com>
Maintainer: VeritasGraph Team
License: MIT
License-File: LICENSE
Keywords: ai-reasoning,document-analysis,enterprise-ai,graph-database,graphrag,hierarchical-tree,knowledge-graph,llm,multimodal,ollama,pdf,rag,retrieval-augmented-generation,table-of-contents,vision
Classifier: Development Status :: 4 - Beta
Classifier: Intended Audience :: Developers
Classifier: Intended Audience :: Information Technology
Classifier: Intended Audience :: Science/Research
Classifier: License :: OSI Approved :: MIT License
Classifier: Operating System :: OS Independent
Classifier: Programming Language :: Python :: 3
Classifier: Programming Language :: Python :: 3.10
Classifier: Programming Language :: Python :: 3.11
Classifier: Programming Language :: Python :: 3.12
Classifier: Programming Language :: Python :: 3.13
Classifier: Topic :: Scientific/Engineering :: Artificial Intelligence
Classifier: Topic :: Software Development :: Libraries :: Python Modules
Classifier: Topic :: Text Processing :: General
Classifier: Typing :: Typed
Requires-Python: >=3.10
Requires-Dist: matplotlib>=3.7.0
Requires-Dist: networkx>=3.0
Requires-Dist: numpy>=1.24.0
Requires-Dist: ollama>=0.2.0
Requires-Dist: pdf2image>=1.16.0
Requires-Dist: pillow>=10.0.0
Requires-Dist: python-dotenv>=1.0.0
Provides-Extra: all
Requires-Dist: black>=23.0.0; extra == 'all'
Requires-Dist: gradio>=4.0.0; extra == 'all'
Requires-Dist: graphrag>=0.3.0; extra == 'all'
Requires-Dist: mypy>=1.0.0; extra == 'all'
Requires-Dist: pandas>=2.0.0; extra == 'all'
Requires-Dist: pre-commit>=3.0.0; extra == 'all'
Requires-Dist: pytest-asyncio>=0.21.0; extra == 'all'
Requires-Dist: pytest-cov>=4.0.0; extra == 'all'
Requires-Dist: pytest>=7.0.0; extra == 'all'
Requires-Dist: pyvis>=0.3.0; extra == 'all'
Requires-Dist: ruff>=0.1.0; extra == 'all'
Requires-Dist: tiktoken>=0.5.0; extra == 'all'
Requires-Dist: trafilatura>=1.6.0; extra == 'all'
Requires-Dist: youtube-transcript-api>=0.6.0; extra == 'all'
Requires-Dist: yt-dlp>=2024.1.0; extra == 'all'
Provides-Extra: dev
Requires-Dist: black>=23.0.0; extra == 'dev'
Requires-Dist: mypy>=1.0.0; extra == 'dev'
Requires-Dist: pre-commit>=3.0.0; extra == 'dev'
Requires-Dist: pytest-asyncio>=0.21.0; extra == 'dev'
Requires-Dist: pytest-cov>=4.0.0; extra == 'dev'
Requires-Dist: pytest>=7.0.0; extra == 'dev'
Requires-Dist: ruff>=0.1.0; extra == 'dev'
Provides-Extra: graphrag
Requires-Dist: graphrag>=0.3.0; extra == 'graphrag'
Requires-Dist: tiktoken>=0.5.0; extra == 'graphrag'
Provides-Extra: ingest
Requires-Dist: trafilatura>=1.6.0; extra == 'ingest'
Requires-Dist: youtube-transcript-api>=0.6.0; extra == 'ingest'
Requires-Dist: yt-dlp>=2024.1.0; extra == 'ingest'
Provides-Extra: web
Requires-Dist: gradio>=4.0.0; extra == 'web'
Requires-Dist: pandas>=2.0.0; extra == 'web'
Requires-Dist: pyvis>=0.3.0; extra == 'web'
